{"cameraMode":{"drawMode":0,"name":"Shaded","section":"Shading Mode"},"sceneLighting":true,"audioPlay":false,"sceneViewState":{"m_AlwaysRefresh":false,"showFog":true,"showSkybox":true,"showFlares":true,"showImageEffects":true,"showParticleSystems":true,"showVisualEffectGraphs":true,"m_FxEnabled":true},"in2DMode":false,"pivot":{"x":0.976801872253418,"y":1.1028891801834107,"z":0.01784774661064148},"rotation":{"x":0.04293011873960495,"y":-0.7330820560455322,"z":0.046473268419504169,"w":0.677195131778717},"size":1.4089387655258179,"orthographic":false}